karel_robot/__init__.py
karel_robot/board.py
karel_robot/robot.py
karel_robot/tiles.py
karel_robot/window.py
karel_robot/parsers/__init__.py
karel_robot/parsers/cli_arguments.py
karel_robot/parsers/interpret.py
karel_robot/parsers/map.py
karel_robot/run/__init__.py
karel_robot/run/functions.py
karel_robot/run/interactive.py
karel_robot/run/main.py
karel_robot/run/startup.py
karel_robot-1.1.0.dist-info/LICENSE
karel_robot-1.1.0.dist-info/METADATA
karel_robot-1.1.0.dist-info/WHEEL
karel_robot-1.1.0.dist-info/entry_points.txt
karel_robot-1.1.0.dist-info/top_level.txt
karel_robot-1.1.0.dist-info/RECORD
