Metadata-Version: 2.1
Name: karel-robot
Version: 1.1.0
Summary: Karel the Robot simple library and interactive executable
Home-page: https://github.com/xsebek/karel
Author: Ondřej Šebek
Author-email: xsebek@fi.muni.cz
License: UNKNOWN
Platform: UNKNOWN
Classifier: Programming Language :: Python :: 3.7
Classifier: License :: OSI Approved :: GNU General Public License v3 or later (GPLv3+)
Classifier: Operating System :: OS Independent
Classifier: Environment :: Console :: Curses
Classifier: Topic :: Education
Classifier: Intended Audience :: Education 
Requires-Python: >=3.6
Requires-Dist: windows-curses (>=2.2) ; platform_system == "Windows"
